mqtt_to_influx/__init__.py
mqtt_to_influx/config.py
mqtt_to_influx/daemon.py
mqtt_to_influx/homegear.py
mqtt_to_influx/influx_client.py
mqtt_to_influx/mh_sensor_v1.py
mqtt_to_influx/parse_mqtt_data.py
mqtt_to_influx/parse_options.py
mqtt_to_influx/rel_h_t_abs.py
mqtt_to_influx/scc_ampel.py
mqtt_to_influx/tasmota_pid.py
mqtt_to_influx/tasmota_sensor_am2301.py
mqtt_to_influx/tasmota_sensor_am2301_state.py
mqtt_to_influx/tasmota_sensor_bh1750.py
mqtt_to_influx/tasmota_sensor_ds18b20.py
mqtt_to_influx/weather_ka.py
mqtt_to_influx-0.3.7.dist-info/LICENSE
mqtt_to_influx-0.3.7.dist-info/METADATA
mqtt_to_influx-0.3.7.dist-info/WHEEL
mqtt_to_influx-0.3.7.dist-info/entry_points.txt
mqtt_to_influx-0.3.7.dist-info/pbr.json
mqtt_to_influx-0.3.7.dist-info/top_level.txt
mqtt_to_influx-0.3.7.dist-info/RECORD
