Metadata-Version: 2.1
Name: mqtt-to-influx
Version: 0.3.7
Summary: Collect mqtt data, apply type specific conversion and stuff that into an influx DB
Home-page: https://none
Author: Marcus Hardt
Author-email: marcus@hardt-it.de
License: MIT
Project-URL: Bug Tracker, https://none
Project-URL: Documentation, https://none
Platform: UNKNOWN
Classifier: Development Status :: 3 - Alpha
Classifier: Environment :: Console
Classifier: Intended Audience :: Developers
Classifier: Intended Audience :: Information Technology
Classifier: Intended Audience :: Science/Research
Classifier: License :: OSI Approved :: MIT License
Classifier: Operating System :: OS Independent
Classifier: Natural Language :: English
Classifier: Programming Language :: Python
Classifier: Programming Language :: Python :: 3
Classifier: Topic :: Utilities
Requires-Dist: paho-mqtt
Requires-Dist: influxdb
Requires-Dist: configargparse
Requires-Dist: configparser
